bosch/control_panel/cc880p/__init__.py
bosch/control_panel/cc880p/cp.py
bosch/control_panel/cc880p/utils.py
bosch/control_panel/cc880p/version.py
bosch/control_panel/cc880p/cli/__init__.py
bosch/control_panel/cc880p/cli/cli.py
bosch/control_panel/cc880p/cli/cmds.py
bosch/control_panel/cc880p/cli/parser.py
bosch/control_panel/cc880p/models/__init__.py
bosch/control_panel/cc880p/models/callbacks.py
bosch/control_panel/cc880p/models/constants.py
bosch/control_panel/cc880p/models/cp.py
bosch/control_panel/cc880p/models/errors.py
bosch/control_panel/cc880p/models/listener.py
bosch/control_panel/cc880p/models/requests.py
bosch/control_panel/cc880p/models/responses.py
bosch_control_panel_cc880p-4.0.0.dist-info/LICENSE
bosch_control_panel_cc880p-4.0.0.dist-info/METADATA
bosch_control_panel_cc880p-4.0.0.dist-info/WHEEL
bosch_control_panel_cc880p-4.0.0.dist-info/entry_points.txt
bosch_control_panel_cc880p-4.0.0.dist-info/top_level.txt
bosch_control_panel_cc880p-4.0.0.dist-info/RECORD
