Metadata-Version: 2.1
Name: bosch-control-panel-cc880p
Version: 4.0.0
Summary: Library to interface with the old CC880p Bosch COntrol Panels
Home-page: https://github.com/hgomes88/bosch-control-panel-cc880p
Author: Hugo Gomes
Author-email: hgomes88@gmail.com
Project-URL: Tracker, https://github.com/hgomes88/bosch-control-panel-cc880p/issues
Project-URL: Download, https://pypi.org/project/bosch-control-panel-cc880p/
Classifier: Programming Language :: Python :: 3
Classifier: License :: OSI Approved :: Apache Software License
Classifier: Operating System :: OS Independent
Requires-Python: >=3.8
License-File: LICENSE
Provides-Extra: dev
Requires-Dist: twine (==4.0.0) ; extra == 'dev'
Requires-Dist: build (==0.7.0) ; extra == 'dev'
Requires-Dist: pytest (==7.1.1) ; extra == 'dev'
Requires-Dist: pytest-asyncio (==0.18.3) ; extra == 'dev'
Requires-Dist: pytest-mock (==3.10.0) ; extra == 'dev'
Requires-Dist: pre-commit (==2.18.1) ; extra == 'dev'
Requires-Dist: autopep8 (==1.6.0) ; extra == 'dev'
Requires-Dist: flake8 (==4.0.1) ; extra == 'dev'
Requires-Dist: mypy (==0.942) ; extra == 'dev'
